flask_huey/__init__.py
flask_huey/cli.py
flask_huey-0.0.1.dist-info/entry_points.txt
flask_huey-0.0.1.dist-info/LICENSE
flask_huey-0.0.1.dist-info/WHEEL
flask_huey-0.0.1.dist-info/METADATA
flask_huey-0.0.1.dist-info/RECORD
